{
  "name": " B-3  11  ",
  "algorithm": 32,
  "feedback": 1,
  "lfo": {
    "wave": "sine",
    "speed": 43,
    "delay": 0,
    "pitchModDepth": 9,
    "amDepth": "18",
    "sync": "off",
    "pitchModSensitivity": 0
  },
  "oscillatorKeySync": "Off",
  "pitchEG": {
    "rate1": 99,
    "rate2": 80,
    "rate3": 75,
    "rate4": 60,
    "level1": 50,
    "level2": 50,
    "level3": 50,
    "level4": 50
  },
  "transpose": "C3",
  "operators": [
    {
      "amSensitivity": 3,
      "oscillatorMode": "ratio",
      "frequency": 0,
      "detune": -2,
      "eg": {
        "rate1": 99,
        "rate2": 80,
        "rate3": 22,
        "rate4": 90,
        "level1": 99,
        "level2": 99,
        "level3": 99,
        "level4": 0
      },
      "keyboardLevelScaling": {
        "breakpoint": "A-1",
        "leftCurve": "-LIN",
        "rightCurve": "-LIN",
        "leftDepth": 0,
        "rightDepth": 0
      },
      "keyboardRateScaling": 0,
      "outputLevel": 99,
      "keyVelocitySensitivity": 0
    },
    {
      "amSensitivity": 3,
      "oscillatorMode": "ratio",
      "frequency": 1,
      "detune": -6,
      "eg": {
        "rate1": 99,
        "rate2": 20,
        "rate3": 22,
        "rate4": 90,
        "level1": 99,
        "level2": 99,
        "level3": 99,
        "level4": 0
      },
      "keyboardLevelScaling": {
        "breakpoint": "A-1",
        "leftCurve": "-LIN",
        "rightCurve": "-LIN",
        "leftDepth": 0,
        "rightDepth": 0
      },
      "keyboardRateScaling": 0,
      "outputLevel": 99,
      "keyVelocitySensitivity": 0
    },
    {
      "amSensitivity": 3,
      "oscillatorMode": "ratio",
      "frequency": 1,
      "detune": 4,
      "eg": {
        "rate1": 99,
        "rate2": 80,
        "rate3": 54,
        "rate4": 82,
        "level1": 99,
        "level2": 99,
        "level3": 99,
        "level4": 0
      },
      "keyboardLevelScaling": {
        "breakpoint": "A-1",
        "leftCurve": "-LIN",
        "rightCurve": "-LIN",
        "leftDepth": 0,
        "rightDepth": 0
      },
      "keyboardRateScaling": 0,
      "outputLevel": 99,
      "keyVelocitySensitivity": 0
    },
    {
      "amSensitivity": 3,
      "oscillatorMode": "ratio",
      "frequency": 3,
      "detune": 5,
      "eg": {
        "rate1": 99,
        "rate2": 80,
        "rate3": 22,
        "rate4": 90,
        "level1": 99,
        "level2": 99,
        "level3": 99,
        "level4": 0
      },
      "keyboardLevelScaling": {
        "breakpoint": "A-1",
        "leftCurve": "-LIN",
        "rightCurve": "-LIN",
        "leftDepth": 0,
        "rightDepth": 0
      },
      "keyboardRateScaling": 0,
      "outputLevel": 99,
      "keyVelocitySensitivity": 0
    },
    {
      "amSensitivity": 3,
      "oscillatorMode": "ratio",
      "frequency": 2,
      "detune": 2,
      "eg": {
        "rate1": 99,
        "rate2": 80,
        "rate3": 22,
        "rate4": 90,
        "level1": 99,
        "level2": 99,
        "level3": 99,
        "level4": 0
      },
      "keyboardLevelScaling": {
        "breakpoint": "A-1",
        "leftCurve": "-LIN",
        "rightCurve": "-LIN",
        "leftDepth": 0,
        "rightDepth": 0
      },
      "keyboardRateScaling": 0,
      "outputLevel": 99,
      "keyVelocitySensitivity": 0
    },
    {
      "amSensitivity": 3,
      "oscillatorMode": "ratio",
      "frequency": 3,
      "detune": -1,
      "eg": {
        "rate1": 99,
        "rate2": 0,
        "rate3": 0,
        "rate4": 90,
        "level1": 99,
        "level2": 99,
        "level3": 99,
        "level4": 0
      },
      "keyboardLevelScaling": {
        "breakpoint": "A-1",
        "leftCurve": "-LIN",
        "rightCurve": "-LIN",
        "leftDepth": 0,
        "rightDepth": 0
      },
      "keyboardRateScaling": 0,
      "outputLevel": 99,
      "keyVelocitySensitivity": 0
    }
  ]
}