{
  "name": "E.P.& BR B",
  "algorithm": 5,
  "feedback": 7,
  "lfo": {
    "wave": "sine",
    "speed": 34,
    "delay": 33,
    "pitchModDepth": 0,
    "amDepth": "0",
    "sync": "off",
    "pitchModSensitivity": 1
  },
  "oscillatorKeySync": "Off",
  "pitchEG": {
    "rate1": 99,
    "rate2": 99,
    "rate3": 99,
    "rate4": 99,
    "level1": 50,
    "level2": 50,
    "level3": 50,
    "level4": 50
  },
  "transpose": "C2",
  "operators": [
    {
      "amSensitivity": 0,
      "oscillatorMode": "fixed",
      "frequency": 1,
      "detune": -7,
      "eg": {
        "rate1": 96,
        "rate2": 23,
        "rate3": 25,
        "rate4": 71,
        "level1": 99,
        "level2": 75,
        "level3": 0,
        "level4": 0
      },
      "keyboardLevelScaling": {
        "breakpoint": "A-1",
        "leftCurve": "-LIN",
        "rightCurve": "-LIN",
        "leftDepth": 0,
        "rightDepth": 0
      },
      "keyboardRateScaling": 3,
      "outputLevel": 95,
      "keyVelocitySensitivity": 2
    },
    {
      "amSensitivity": 0,
      "oscillatorMode": "ratio",
      "frequency": 1,
      "detune": -7,
      "eg": {
        "rate1": 95,
        "rate2": 90,
        "rate3": 26,
        "rate4": 97,
        "level1": 99,
        "level2": 94,
        "level3": 86,
        "level4": 91
      },
      "keyboardLevelScaling": {
        "breakpoint": "A-1",
        "leftCurve": "-LIN",
        "rightCurve": "-LIN",
        "leftDepth": 0,
        "rightDepth": 0
      },
      "keyboardRateScaling": 3,
      "outputLevel": 90,
      "keyVelocitySensitivity": 5
    },
    {
      "amSensitivity": 0,
      "oscillatorMode": "ratio",
      "frequency": 1,
      "detune": -7,
      "eg": {
        "rate1": 95,
        "rate2": 48,
        "rate3": 25,
        "rate4": 60,
        "level1": 99,
        "level2": 94,
        "level3": 0,
        "level4": 0
      },
      "keyboardLevelScaling": {
        "breakpoint": "A2",
        "leftCurve": "-LIN",
        "rightCurve": "-LIN",
        "leftDepth": 36,
        "rightDepth": 0
      },
      "keyboardRateScaling": 3,
      "outputLevel": 94,
      "keyVelocitySensitivity": 4
    },
    {
      "amSensitivity": 0,
      "oscillatorMode": "ratio",
      "frequency": 11,
      "detune": -7,
      "eg": {
        "rate1": 97,
        "rate2": 85,
        "rate3": 44,
        "rate4": 54,
        "level1": 97,
        "level2": 73,
        "level3": 0,
        "level4": 48
      },
      "keyboardLevelScaling": {
        "breakpoint": "G3",
        "leftCurve": "-LIN",
        "rightCurve": "-LIN",
        "leftDepth": 48,
        "rightDepth": 0
      },
      "keyboardRateScaling": 1,
      "outputLevel": 74,
      "keyVelocitySensitivity": 6
    },
    {
      "amSensitivity": 3,
      "oscillatorMode": "ratio",
      "frequency": 1,
      "detune": 0,
      "eg": {
        "rate1": 86,
        "rate2": 99,
        "rate3": 99,
        "rate4": 57,
        "level1": 99,
        "level2": 99,
        "level3": 99,
        "level4": 0
      },
      "keyboardLevelScaling": {
        "breakpoint": "A-1",
        "leftCurve": "-LIN",
        "rightCurve": "-LIN",
        "leftDepth": 0,
        "rightDepth": 0
      },
      "keyboardRateScaling": 3,
      "outputLevel": 99,
      "keyVelocitySensitivity": 0
    },
    {
      "amSensitivity": 3,
      "oscillatorMode": "ratio",
      "frequency": 1,
      "detune": 0,
      "eg": {
        "rate1": 99,
        "rate2": 74,
        "rate3": 45,
        "rate4": 54,
        "level1": 99,
        "level2": 99,
        "level3": 93,
        "level4": 0
      },
      "keyboardLevelScaling": {
        "breakpoint": "A-1",
        "leftCurve": "-LIN",
        "rightCurve": "-LIN",
        "leftDepth": 0,
        "rightDepth": 0
      },
      "keyboardRateScaling": 0,
      "outputLevel": 85,
      "keyVelocitySensitivity": 0
    }
  ]
}