{
  "name": "DYNO MYTE ",
  "algorithm": 5,
  "feedback": 1,
  "lfo": {
    "wave": "triangle",
    "speed": 22,
    "delay": 0,
    "pitchModDepth": 9,
    "amDepth": "0",
    "sync": "on",
    "pitchModSensitivity": 3
  },
  "oscillatorKeySync": "Off",
  "pitchEG": {
    "rate1": 94,
    "rate2": 67,
    "rate3": 95,
    "rate4": 60,
    "level1": 50,
    "level2": 50,
    "level3": 50,
    "level4": 50
  },
  "transpose": "C3",
  "operators": [
    {
      "amSensitivity": 0,
      "oscillatorMode": "ratio",
      "frequency": 1,
      "detune": 0,
      "eg": {
        "rate1": 96,
        "rate2": 25,
        "rate3": 25,
        "rate4": 49,
        "level1": 99,
        "level2": 75,
        "level3": 0,
        "level4": 0
      },
      "keyboardLevelScaling": {
        "breakpoint": "C3",
        "leftCurve": "+LIN",
        "rightCurve": "-EXP",
        "leftDepth": 0,
        "rightDepth": 0
      },
      "keyboardRateScaling": 3,
      "outputLevel": 99,
      "keyVelocitySensitivity": 2
    },
    {
      "amSensitivity": 0,
      "oscillatorMode": "ratio",
      "frequency": 26,
      "detune": 0,
      "eg": {
        "rate1": 99,
        "rate2": 46,
        "rate3": 35,
        "rate4": 35,
        "level1": 80,
        "level2": 75,
        "level3": 55,
        "level4": 0
      },
      "keyboardLevelScaling": {
        "breakpoint": "C3",
        "leftCurve": "-LIN",
        "rightCurve": "+EXP",
        "leftDepth": 99,
        "rightDepth": 99
      },
      "keyboardRateScaling": 4,
      "outputLevel": 99,
      "keyVelocitySensitivity": 7
    },
    {
      "amSensitivity": 0,
      "oscillatorMode": "ratio",
      "frequency": 1,
      "detune": 0,
      "eg": {
        "rate1": 96,
        "rate2": 25,
        "rate3": 25,
        "rate4": 49,
        "level1": 99,
        "level2": 75,
        "level3": 0,
        "level4": 0
      },
      "keyboardLevelScaling": {
        "breakpoint": "C3",
        "leftCurve": "+LIN",
        "rightCurve": "-EXP",
        "leftDepth": 0,
        "rightDepth": 0
      },
      "keyboardRateScaling": 3,
      "outputLevel": 99,
      "keyVelocitySensitivity": 0
    },
    {
      "amSensitivity": 0,
      "oscillatorMode": "ratio",
      "frequency": 8,
      "detune": 0,
      "eg": {
        "rate1": 95,
        "rate2": 84,
        "rate3": 20,
        "rate4": 35,
        "level1": 99,
        "level2": 0,
        "level3": 0,
        "level4": 46
      },
      "keyboardLevelScaling": {
        "breakpoint": "C3",
        "leftCurve": "-EXP",
        "rightCurve": "+EXP",
        "leftDepth": 0,
        "rightDepth": 0
      },
      "keyboardRateScaling": 3,
      "outputLevel": 99,
      "keyVelocitySensitivity": 5
    },
    {
      "amSensitivity": 0,
      "oscillatorMode": "ratio",
      "frequency": 1,
      "detune": -4,
      "eg": {
        "rate1": 95,
        "rate2": 20,
        "rate3": 20,
        "rate4": 44,
        "level1": 99,
        "level2": 95,
        "level3": 0,
        "level4": 0
      },
      "keyboardLevelScaling": {
        "breakpoint": "C3",
        "leftCurve": "-LIN",
        "rightCurve": "-EXP",
        "leftDepth": 0,
        "rightDepth": 40
      },
      "keyboardRateScaling": 3,
      "outputLevel": 99,
      "keyVelocitySensitivity": 2
    },
    {
      "amSensitivity": 0,
      "oscillatorMode": "ratio",
      "frequency": 1,
      "detune": 4,
      "eg": {
        "rate1": 95,
        "rate2": 29,
        "rate3": 20,
        "rate4": 50,
        "level1": 99,
        "level2": 95,
        "level3": 0,
        "level4": 0
      },
      "keyboardLevelScaling": {
        "breakpoint": "C3",
        "leftCurve": "+LIN",
        "rightCurve": "+EXP",
        "leftDepth": 99,
        "rightDepth": 99
      },
      "keyboardRateScaling": 3,
      "outputLevel": 85,
      "keyVelocitySensitivity": 7
    }
  ]
}